setup.py
wwpolytechnique_distributions/Binomialdistribution.py
wwpolytechnique_distributions/Gaussiandistribution.py
wwpolytechnique_distributions/Generaldistribution.py
wwpolytechnique_distributions/__init__.py
wwpolytechnique_distributions.egg-info/PKG-INFO
wwpolytechnique_distributions.egg-info/SOURCES.txt
wwpolytechnique_distributions.egg-info/dependency_links.txt
wwpolytechnique_distributions.egg-info/not-zip-safe
wwpolytechnique_distributions.egg-info/top_level.txt